pymatio/__init__.py
pymatio/libpymatio.cpython-310-x86_64-linux-gnu.so
pymatio/__init__.pyi
pymatio/py.typed
pymatio-0.1.1.dist-info/RECORD
pymatio-0.1.1.dist-info/METADATA
pymatio-0.1.1.dist-info/WHEEL
share/man/man3/zlib.3
share/pkgconfig/zlib.pc
