Metadata-Version: 2.1
Name: pymatio
Version: 0.1.1
Author-Email: zhengmy <zhengmy@ion.ac.cn>
Project-URL: Homepage, https://github.com/myuanz/pymatio
Requires-Python: <3.13,>=3.9
